fsspec_ftps_extension/__init__.py
fsspec_ftps_extension/ftps.py
fsspec_ftps_extension-0.1.0.dist-info/METADATA
fsspec_ftps_extension-0.1.0.dist-info/WHEEL
fsspec_ftps_extension-0.1.0.dist-info/RECORD
