Metadata-Version: 2.1
Name: fsspec-ftps-extension
Version: 0.1.0
Summary: 
Author: overlucker
Author-email: vlyankov@mail.ru
Requires-Python: >=3.10,<4.0
Classifier: Programming Language :: Python :: 3
Classifier: Programming Language :: Python :: 3.10
Classifier: Programming Language :: Python :: 3.11
Classifier: Programming Language :: Python :: 3.12
Requires-Dist: fsspec (>=2024.5.0,<2025.0.0)
